vitae_parser/__init__.py
vitae_parser/main.py
vitae_parser/prompts.py
vitae_parser-2025.12.22074807.dist-info/METADATA
vitae_parser-2025.12.22074807.dist-info/WHEEL
vitae_parser-2025.12.22074807.dist-info/top_level.txt
vitae_parser-2025.12.22074807.dist-info/RECORD
