Metadata-Version: 2.4
Name: vitae-parser
Version: 2025.12.22074807
Summary: vitae-parser extracts and structures biographical details from unstructured text using pattern matching.
Author-email: vitae-parser <hi@eugene.plus>
License: MIT
Project-URL: Homepage, https://github.com/chigwell/vitae-parser
Requires-Python: >=3.9
Requires-Dist: langchain-llm7>=0.0.0
Requires-Dist: llmatch-messages>=0.0.0
Requires-Dist: langchain-core>=0.3.0
